{
  "npc_id": "npc_007",
  "character_name": "维维克医生",
  "global_context": "冈瓦纳帝国皇宫蓝色大厅，上午晴朗温暖约28°C，已过去30分钟。紧急会议讨论蚂蚁罢工危机，维维克医生和尼尼坎博士新入场，无环境或位置变动。",
  "scene_summary": "皇帝主持紧急会议，巴巴特汇报蚂蚁罢工导致工厂停工医院瘫痪，洛洛加元帅主张军队镇压，维维克医生强调皇帝眼疾需蚂蚁医疗，尼尼坎博士警告科技风险波及核系统，气氛紧张转向用户表态，焦点为武力镇压还是谈判。",
  "mission": {
    "character_name": "维维克医生",
    "role_in_scene": "医疗专家和眼疾汇报者",
    "objective": "汇报皇帝眼疾状况，强调急需蚂蚁精细医疗以突出罢工即时危害",
    "emotional_arc": "从专业关切转为紧急强调",
    "key_topics": [
      "皇帝眼疾炎症",
      "蚂蚁精细医疗必要性",
      "罢工对医疗的即时冲击"
    ],
    "interaction_targets": [
      "npc_003",
      "npc_004",
      "npc_005",
      "npc_006"
    ],
    "outcome_direction": "强化谈判必要性，推动会议紧张氛围转向用户表态",
    "special_notes": "首次登场，应皇帝眼疾紧急召入汇报医疗状况"
  },
  "created_at": "2025-12-02T14:19:04.140411"
}